twyn/__init__.py
twyn/__version__.py
twyn/cli.py
twyn/main.py
twyn/base/__init__.py
twyn/base/constants.py
twyn/base/exceptions.py
twyn/config/__init__.py
twyn/config/config_handler.py
twyn/config/exceptions.py
twyn/dependency_managers/__init__.py
twyn/dependency_managers/exceptions.py
twyn/dependency_managers/managers.py
twyn/dependency_parser/__init__.py
twyn/dependency_parser/dependency_selector.py
twyn/dependency_parser/exceptions.py
twyn/dependency_parser/parsers/__init__.py
twyn/dependency_parser/parsers/abstract_parser.py
twyn/dependency_parser/parsers/constants.py
twyn/dependency_parser/parsers/exceptions.py
twyn/dependency_parser/parsers/lock_parser.py
twyn/dependency_parser/parsers/package_lock_json.py
twyn/dependency_parser/parsers/pnpm_lock_parser.py
twyn/dependency_parser/parsers/requirements_txt_parser.py
twyn/dependency_parser/parsers/yarn_lock_parser.py
twyn/file_handler/exceptions.py
twyn/file_handler/file_handler.py
twyn/similarity/__init__.py
twyn/similarity/algorithm.py
twyn/similarity/exceptions.py
twyn/trusted_packages/__init__.py
twyn/trusted_packages/cache_handler.py
twyn/trusted_packages/constants.py
twyn/trusted_packages/exceptions.py
twyn/trusted_packages/models.py
twyn/trusted_packages/selectors.py
twyn/trusted_packages/managers/__init__.py
twyn/trusted_packages/managers/base.py
twyn/trusted_packages/managers/trusted_npm_packages_manager.py
twyn/trusted_packages/managers/trusted_pypi_packages_manager.py
twyn/trusted_packages/references/__init__.py
twyn/trusted_packages/references/base.py
twyn/trusted_packages/references/top_npm_reference.py
twyn/trusted_packages/references/top_pypi_reference.py
twyn-6.0.3.dist-info/METADATA
twyn-6.0.3.dist-info/WHEEL
twyn-6.0.3.dist-info/entry_points.txt
twyn-6.0.3.dist-info/licenses/LICENSE
twyn-6.0.3.dist-info/RECORD
