Metadata-Version: 2.4
Name: twyn
Version: 6.0.3
Summary: Security tool against dependency typosquatting attacks
Author: Ludo van Orden, Dmitrii Fedotov
Author-email: Daniel Sanz <imsdn4z@gmail.com>, Sergio Castillo <s.cast.lara@gmail.com>
Maintainer-email: Daniel Sanz <imsdn4z@gmail.com>, Sergio Castillo <s.cast.lara@gmail.com>
License-File: LICENSE
Requires-Python: <4,>=3.10
Requires-Dist: pydantic<3.0.0,>=2.11.7
Requires-Dist: pyparsing<4.0.0,>=3.2.3
Requires-Dist: pyyaml>=6.0.2
Requires-Dist: rapidfuzz<4.0.0,>=2.13.7
Requires-Dist: requests<3.0.0,>=2.32.4
Requires-Dist: tomlkit<0.14.0,>=0.11.6
Provides-Extra: cli
Requires-Dist: click<9.0.0,>=8.1.8; extra == 'cli'
Requires-Dist: rich<15.0.0,>=14.0.0; extra == 'cli'
